django_secure_signature/__init__.py
django_secure_signature/_settings.py
django_secure_signature/middleware.py
django_secure_signature/settings.py
django_secure_signature/utils.py
django_secure_signature-0.2.2.dist-info/DESCRIPTION.rst
django_secure_signature-0.2.2.dist-info/METADATA
django_secure_signature-0.2.2.dist-info/RECORD
django_secure_signature-0.2.2.dist-info/WHEEL
django_secure_signature-0.2.2.dist-info/metadata.json
django_secure_signature-0.2.2.dist-info/top_level.txt
