Metadata-Version: 2.0
Name: django-secure-signature
Version: 0.2.2
Summary: Secure data signing for django apps, ready-to-use (allegedly).
Home-page: https://github.com/kornov-rooman/django-secure-signature
Author: Kornov Rooman
Author-email: kornov.rooman@gmail.com
License: MIT
Platform: UNKNOWN
Classifier: Environment :: Web Environment
Classifier: Intended Audience :: Developers
Classifier: Operating System :: OS Independent
Classifier: Programming Language :: Python
Classifier: Programming Language :: Python :: 3
Classifier: Programming Language :: Python :: 3.4
Classifier: Programming Language :: Python :: 3.5
Classifier: Programming Language :: Python :: 3.6
Classifier: License :: OSI Approved :: MIT License
Requires: django
Requires: typing
Requires-Python: >=3.4
